[
  {
    "Algorithm": "IMM",
    "Counting": [
      20.1537
    ],
    "DiffusionModel": "IC",
    "Epsilon": 0.25,
    "FindMostInfluentialSet": 0.0,
    "GenerateRRRSets": 1344.4948,
    "Input": "Cit-HepPh.txt",
    "K": 75,
    "L": 1,
    "NumGPUWalkWorkers": 0,
    "NumThreads": 1,
    "NumWalkWorkers": 8,
    "Output": "Cit-HepPh_2_75.json",
    "Pivoting": [
      8.328099999999997
    ],
    "RRRSetSizeBytes": 0,
    "Seeds": [
      19547,
      29423,
      17481,
      34335,
      31331,
      32557,
      16067,
      32396,
      7363,
      24839,
      29778,
      31883,
      24500,
      32617,
      1289,
      32101,
      33259,
      33601,
      30304,
      371,
      31469,
      32281,
      27805,
      24758,
      32053,
      30469,
      34502,
      23072,
      17963,
      19965,
      8188,
      34234,
      23184,
      25430,
      34318,
      15985,
      11082,
      32695,
      30506,
      26229,
      32837,
      29893,
      30872,
      27292,
      33345,
      20607,
      34496,
      28847,
      31902,
      34008,
      34449,
      28446,
      27079,
      23965,
      27309,
      19979,
      29019,
      28814,
      16898,
      24918,
      34125,
      29781,
      1132,
      30240,
      34323,
      33784,
      34242,
      31325,
      26648,
      29456,
      26046,
      29543,
      29519,
      33386,
      33686
    ],
    "Theta": 31004,
    "ThetaEstimation": 1805.2734,
    "ThetaEstimationGenerateRRR": [
      1774.757
    ],
    "ThetaEstimationMostInfluential": [
      30.4615
    ],
    "ThetaPrimeDeltas": [
      17779
    ],
    "Total": 9383.1347
  },
  {
    "Algorithm": "IMM",
    "Counting": [
      18.5375
    ],
    "DiffusionModel": "IC",
    "Epsilon": 0.25,
    "FindMostInfluentialSet": 0.0,
    "GenerateRRRSets": 1939.5523,
    "Input": "Cit-HepPh.txt",
    "K": 75,
    "L": 1,
    "NumGPUWalkWorkers": 0,
    "NumThreads": 1,
    "NumWalkWorkers": 8,
    "Output": "Cit-HepPh_2_75.json",
    "Pivoting": [
      6.0962
    ],
    "RRRSetSizeBytes": 0,
    "Seeds": [
      19547,
      29423,
      17481,
      34335,
      31331,
      32557,
      16067,
      32396,
      7363,
      24839,
      29778,
      31883,
      24500,
      32617,
      1289,
      32101,
      33259,
      33601,
      30304,
      371,
      31469,
      32281,
      27805,
      24758,
      32053,
      30469,
      34502,
      23072,
      17963,
      19965,
      8188,
      34234,
      23184,
      25430,
      34318,
      15985,
      11082,
      32695,
      30506,
      26229,
      32837,
      29893,
      30872,
      27292,
      33345,
      20607,
      34496,
      28847,
      31902,
      34008,
      34449,
      28446,
      27079,
      23965,
      27309,
      19979,
      29019,
      28814,
      16898,
      24918,
      34125,
      29781,
      1132,
      30240,
      34323,
      33784,
      34242,
      31325,
      26648,
      29456,
      26046,
      29543,
      29519,
      33386,
      33686
    ],
    "Theta": 26769,
    "ThetaEstimation": 3886.5315,
    "ThetaEstimationGenerateRRR": [
      3860.018
    ],
    "ThetaEstimationMostInfluential": [
      26.5046
    ],
    "ThetaPrimeDeltas": [
      17697
    ],
    "Total": 0.0
  }
]